metadata_inspector/__init__.py
metadata_inspector/_slk.py
metadata_inspector/_version.py
metadata_inspector/utils.py
metadata_inspector/tests/conftest.py
metadata_inspector/tests/test_inspector.py
metadata_inspector-2025.7.11.dist-info/entry_points.txt
metadata_inspector-2025.7.11.dist-info/licenses/LICENSE
metadata_inspector-2025.7.11.dist-info/WHEEL
metadata_inspector-2025.7.11.dist-info/METADATA
metadata_inspector-2025.7.11.dist-info/RECORD
